<core:FragmentDefinition xmlns:core="sap.ui.core" controllerName="com.sap.build.standard.controleDeServicos.controller.Descricao" xmlns="sap.m">
    <Dialog horizontalScrolling="true" showHeader="true" state="None" stretch="false" title="Descrição" type="Standard" verticalScrolling="true">
        <content>
            <TextArea rows="2" cols="40" maxLength="0" wrapping="None" enabled="true" required="false" valueStateText="Invalid entry" visible="true"/>
        </content>
        <beginButton/>
        <buttons>
            <Button text="OK" type="Default" iconFirst="true" width="auto" enabled="true" visible="true" iconDensityAware="false" press="_onButtonPress"/>
        </buttons>
        <customHeader/>
        <endButton/>
        <subHeader/>
    </Dialog>
</core:FragmentDefinition>
